grimoire_logging/__init__.py
grimoire_logging/core.py
grimoire_logging-0.1.0.dist-info/METADATA
grimoire_logging-0.1.0.dist-info/WHEEL
grimoire_logging-0.1.0.dist-info/licenses/LICENSE
grimoire_logging-0.1.0.dist-info/RECORD
