Metadata-Version: 2.4
Name: grimoire-logging
Version: 0.1.0
Summary: Flexible logging utilities with dependency injection support for use in GRIMOIRE
Project-URL: Homepage, https://github.com/wyrdbound/grimoire-logging
Project-URL: Documentation, https://github.com/wyrdbound/grimoire-logging#readme
Project-URL: Repository, https://github.com/wyrdbound/grimoire-logging.git
Project-URL: Issues, https://github.com/wyrdbound/grimoire-logging/issues
Project-URL: Changelog, https://github.com/wyrdbound/grimoire-logging/releases
Author-email: The Wyrd One <wyrdbound@proton.me>
Maintainer-email: The Wyrd One <wyrdbound@proton.me>
License-Expression: MIT
License-File: LICENSE
Keywords: dependency-injection,grimoire,logging,rpg,tabletop,thread-safe
Classifier: Development Status :: 4 - Beta
Classifier: Intended Audience :: Developers
Classifier: License :: OSI Approved :: MIT License
Classifier: Operating System :: OS Independent
Classifier: Programming Language :: Python :: 3
Classifier: Programming Language :: Python :: 3.8
Classifier: Programming Language :: Python :: 3.9
Classifier: Programming Language :: Python :: 3.10
Classifier: Programming Language :: Python :: 3.11
Classifier: Programming Language :: Python :: 3.12
Classifier: Topic :: Games/Entertainment :: Role-Playing
Classifier: Topic :: Software Development :: Libraries :: Python Modules
Classifier: Topic :: System :: Logging
Classifier: Typing :: Typed
Requires-Python: >=3.8
Provides-Extra: dev
Requires-Dist: build>=0.10.0; extra == 'dev'
Requires-Dist: mypy>=1.0; extra == 'dev'
Requires-Dist: pytest-asyncio>=0.21.0; extra == 'dev'
Requires-Dist: pytest-cov>=4.0; extra == 'dev'
Requires-Dist: pytest>=7.0; extra == 'dev'
Requires-Dist: ruff>=0.1.0; extra == 'dev'
Requires-Dist: twine>=4.0.0; extra == 'dev'
